cms/__init__.py
cms/api/__init__.py
cms/api/apps.py
cms/api/concurrency.py
cms/api/exceptions.py
cms/api/filters.py
cms/api/ordering.py
cms/api/pagination.py
cms/api/permissions.py
cms/api/serializers.py
cms/api/settings.py
cms/api/urls.py
cms/api/utils.py
cms/api/migrations/__init__.py
cms/api/templates/redoc.html
cms/api/templates/rest_framework/api.html
cms/api/tests/__init__.py
cms/api/tests/test_carousel.py
cms/api/tests/test_carousel_item.py
cms/api/tests/test_carousel_item_link.py
cms/api/tests/test_carousel_item_link_localization.py
cms/api/tests/test_carousel_item_localization.py
cms/api/tests/test_contact.py
cms/api/tests/test_contact_info.py
cms/api/tests/test_contact_info_localization.py
cms/api/tests/test_contact_localization.py
cms/api/tests/test_lock.py
cms/api/tests/test_media.py
cms/api/tests/test_media_collection.py
cms/api/tests/test_media_collection_item.py
cms/api/tests/test_menu.py
cms/api/tests/test_menu_item.py
cms/api/tests/test_menu_item_localization.py
cms/api/tests/test_page.py
cms/api/tests/test_page_block.py
cms/api/tests/test_page_carousel.py
cms/api/tests/test_page_contact.py
cms/api/tests/test_page_heading.py
cms/api/tests/test_page_heading_localization.py
cms/api/tests/test_page_link.py
cms/api/tests/test_page_localization.py
cms/api/tests/test_page_media.py
cms/api/tests/test_page_media_collection.py
cms/api/tests/test_page_menu.py
cms/api/tests/test_page_publication.py
cms/api/tests/test_page_related.py
cms/api/tests/test_publication.py
cms/api/tests/test_publication_attachment.py
cms/api/tests/test_publication_block.py
cms/api/tests/test_publication_link.py
cms/api/tests/test_publication_localization.py
cms/api/tests/test_publication_media_collection.py
cms/api/tests/test_publication_related.py
cms/api/tests/test_redis_locks.py
cms/api/tests/test_template_block.py
cms/api/tests/test_user.py
cms/api/tests/test_webpath.py
cms/api/tests/test_webpath_pub_contexts.py
cms/api/tests/test_website.py
cms/api/views/__init__.py
unicms-0.30.2.dist-info/AUTHORS
unicms-0.30.2.dist-info/LICENSE
unicms-0.30.2.dist-info/METADATA
unicms-0.30.2.dist-info/WHEEL
unicms-0.30.2.dist-info/dependency_links.txt
unicms-0.30.2.dist-info/top_level.txt
unicms-0.30.2.dist-info/RECORD
